SeasonalImpute/__init__.py
SeasonalImpute/imputation.py
seasonalimpute-0.1.0.dist-info/METADATA
seasonalimpute-0.1.0.dist-info/WHEEL
seasonalimpute-0.1.0.dist-info/licenses/LICENSE
seasonalimpute-0.1.0.dist-info/RECORD
