Metadata-Version: 2.4
Name: SeasonalImpute
Version: 0.1.0
Summary: A Python package for imputing missing values in time series data using seasonal weighted averages.
Project-URL: Homepage, https://github.com/hanifkia/SeasonalImpute
Project-URL: Repository, https://github.com/hanifkia/SeasonalImpute.git
Project-URL: Issues, https://github.com/hanifkia/SeasonalImpute/issues
Author-email: Hanif Kia <kia.hanif@gmail.com>
License: MIT License
License-File: LICENSE
Classifier: License :: OSI Approved :: MIT License
Classifier: Operating System :: OS Independent
Classifier: Programming Language :: Python :: 3
Requires-Python: >=3.8
Requires-Dist: gluonts>=0.12
Requires-Dist: numpy>=1.20
